yalisp/__init__.py
yalisp/__main__.py
yalisp/core.py
yalisp/lisp.py
yalisp/py_ast.py
yalisp-0.1.0.dist-info/LICENSE
yalisp-0.1.0.dist-info/WHEEL
yalisp-0.1.0.dist-info/METADATA
yalisp-0.1.0.dist-info/RECORD
