Metadata-Version: 2.1
Name: yalisp
Version: 0.1.0
Summary: Lisp inside yaml
License: MIT
Author: Aleksey Ploskov
Requires-Python: >=3.9,<4.0
Classifier: License :: OSI Approved :: MIT License
Classifier: Programming Language :: Python :: 3
Classifier: Programming Language :: Python :: 3.10
Classifier: Programming Language :: Python :: 3.9
Requires-Dist: PyYAML (>=6.0,<7.0)
